LICENSE.txt
MANIFEST.in
README.rst
requirements.txt
setup.cfg
setup.py
doc/Makefile
doc/conf.py
doc/datagen.1
doc/index.rst
doc/objects.inv
doc/rst/install.rst
doc/rst/module.rst
doc/rst/refman.rst
doc/rst/tutor.rst
doc/rst/install/extensions.rst
doc/rst/install/ext/datagen.rst
doc/rst/module/extensions.rst
doc/rst/module/ext/datagen/asn1codec.rst
doc/rst/module/ext/datagen/datagen.rst
doc/rst/module/ext/datagen/jsongen.rst
doc/rst/module/ext/datagen/main.rst
doc/rst/module/ext/datagen/selenium.rst
doc/rst/module/ext/datagen/serializer.rst
doc/rst/module/ext/datagen/xmlgen.rst
doc/rst/refman/ext/datagen.rst
doc/rst/tutor/extensions.rst
doc/rst/tutor/ext/datagen/datagen.rst
doc/rst/tutor/ext/datagen/tut1_asn1.rst
doc/rst/tutor/ext/datagen/tut2_json.rst
doc/rst/tutor/ext/datagen/tut3_xml.rst
doc/rst/tutor/ext/datagen/tut4_serializer.rst
doc/rst/tutor/ext/datagen/tut5_selenium.rst
etc/hydratk/conf.d/hydratk-ext-datagen.conf
src/hydratk/__init__.py
src/hydratk/extensions/__init__.py
src/hydratk/extensions/datagen/__init__.py
src/hydratk/extensions/datagen/asn1codec.py
src/hydratk/extensions/datagen/bootstrapper.py
src/hydratk/extensions/datagen/datagen.py
src/hydratk/extensions/datagen/jsongen.py
src/hydratk/extensions/datagen/serializer.py
src/hydratk/extensions/datagen/xmlgen.py
src/hydratk/extensions/datagen/adapters/__init__.py
src/hydratk/extensions/datagen/adapters/selenium/__init__.py
src/hydratk/extensions/datagen/adapters/selenium/adapter.py
src/hydratk/extensions/datagen/adapters/selenium/config.py
src/hydratk/extensions/datagen/translation/__init__.py
src/hydratk/extensions/datagen/translation/info.py
src/hydratk/extensions/datagen/translation/cs/__init__.py
src/hydratk/extensions/datagen/translation/cs/help.py
src/hydratk/extensions/datagen/translation/cs/messages.py
src/hydratk/extensions/datagen/translation/en/__init__.py
src/hydratk/extensions/datagen/translation/en/help.py
src/hydratk/extensions/datagen/translation/en/messages.py
src/hydratk_ext_datagen.egg-info/PKG-INFO
src/hydratk_ext_datagen.egg-info/SOURCES.txt
src/hydratk_ext_datagen.egg-info/dependency_links.txt
src/hydratk_ext_datagen.egg-info/entry_points.txt
src/hydratk_ext_datagen.egg-info/not-zip-safe
src/hydratk_ext_datagen.egg-info/top_level.txt
tests/travis.yoda
